ind_ticker/__init__.py
ind_ticker/ind_ticker.py
ind_ticker/mutual_funds.py
ind_ticker/nifty_50.py
ind_ticker/stocks.py
ind_ticker/values.py
ind_ticker-0.0.4.dist-info/METADATA
ind_ticker-0.0.4.dist-info/WHEEL
ind_ticker-0.0.4.dist-info/dependency_links.txt
ind_ticker-0.0.4.dist-info/entry_points.txt
ind_ticker-0.0.4.dist-info/top_level.txt
ind_ticker-0.0.4.dist-info/RECORD
