Metadata-Version: 2.1
Name: ind-ticker
Version: 0.0.4
Summary: CLI tool to get data of Indian Stocks and Mutual Funds
Home-page: https://github.com/skamranahmed/indian-ticker-cli
Author: Syed Kamran Ahmed
Author-email: syedkamranahmed14@gmail.com
License: MIT
Platform: UNKNOWN
Classifier: Programming Language :: Python :: 3
Classifier: License :: OSI Approved :: MIT License
Classifier: Operating System :: MacOS
Requires-Python: >=3.7.0
Requires-Dist: click
Requires-Dist: prettytable
Requires-Dist: requests
Requires-Dist: termcolor
